embcli_cohere/__init__.py
embcli_cohere/cohere_model.py
embcli_cohere/py.typed
embcli_cohere-0.1.1.dist-info/METADATA
embcli_cohere-0.1.1.dist-info/WHEEL
embcli_cohere-0.1.1.dist-info/entry_points.txt
embcli_cohere-0.1.1.dist-info/RECORD
