Metadata-Version: 2.4
Name: embcli-cohere
Version: 0.1.1
Summary: cohere plugin for embcli
Project-URL: Repository, https://github.com/mocobeta/embcli
Project-URL: Homepage, https://embcli.mocobeta.dev/
Author-email: Tomoko Uchida <tomoko.uchida.1111@gmail.com>
License: Apache-2.0
Keywords: cli,embeddings,llm,nlp
Classifier: Development Status :: 3 - Alpha
Classifier: Programming Language :: Python :: 3
Classifier: Programming Language :: Python :: 3.10
Classifier: Programming Language :: Python :: 3.11
Classifier: Programming Language :: Python :: 3.12
Classifier: Programming Language :: Python :: 3.13
Classifier: Topic :: Scientific/Engineering :: Artificial Intelligence
Classifier: Topic :: Terminals
Classifier: Topic :: Text Processing :: Linguistic
Classifier: Topic :: Utilities
Requires-Python: >=3.10
Requires-Dist: cohere>=5.15.0
Requires-Dist: embcli-core>=0.1.1
